textfsm_aos/__init__.py
textfsm_aos/parser.py
textfsm_aos/templates/__init__.py
textfsm_aos/templates/ale_aos6_show_802.1x_non-supplicant.textfsm
textfsm_aos/templates/ale_aos6_show_802.1x_non-supplicant_unp.textfsm
textfsm_aos/templates/ale_aos6_show_802.1x_users.textfsm
textfsm_aos/templates/ale_aos6_show_802.1x_users_unp.textfsm
textfsm_aos/templates/ale_aos6_show_chassis.textfsm
textfsm_aos/templates/ale_aos6_show_command-log.textfsm
textfsm_aos/templates/ale_aos6_show_health.textfsm
textfsm_aos/templates/ale_aos6_show_history.textfsm
textfsm_aos/templates/ale_aos6_show_interfaces_status.textfsm
textfsm_aos/templates/ale_aos6_show_ip_interface.textfsm
textfsm_aos/templates/ale_aos6_show_ip_route.textfsm
textfsm_aos/templates/ale_aos6_show_lldp_remote-system.textfsm
textfsm_aos/templates/ale_aos6_show_mac-address-table.textfsm
textfsm_aos/templates/ale_aos6_show_microcode.textfsm
textfsm_aos/templates/ale_aos6_show_ntp_server_status.textfsm
textfsm_aos/templates/ale_aos6_show_snmp_community_map.textfsm
textfsm_aos/templates/ale_aos6_show_snmp_station.textfsm
textfsm_aos/templates/ale_aos6_show_system.textfsm
textfsm_aos/templates/ale_aos6_show_user.textfsm
textfsm_aos/templates/ale_aos6_show_vlan.textfsm
textfsm_aos/templates/ale_aos6_show_vlan_port_mobile.textfsm
textfsm_aos/templates/ale_aos8_history.textfsm
textfsm_aos/templates/ale_aos8_show_arp.textfsm
textfsm_aos/templates/ale_aos8_show_chassis.textfsm
textfsm_aos/templates/ale_aos8_show_cmm.textfsm
textfsm_aos/templates/ale_aos8_show_command-log.textfsm
textfsm_aos/templates/ale_aos8_show_hardware-info.textfsm
textfsm_aos/templates/ale_aos8_show_health.textfsm
textfsm_aos/templates/ale_aos8_show_interfaces.textfsm
textfsm_aos/templates/ale_aos8_show_interfaces_status.textfsm
textfsm_aos/templates/ale_aos8_show_ip_interface.textfsm
textfsm_aos/templates/ale_aos8_show_ip_router_database.textfsm
textfsm_aos/templates/ale_aos8_show_ip_routes.textfsm
textfsm_aos/templates/ale_aos8_show_linkagg.textfsm
textfsm_aos-1.1.3.dist-info/LICENSE
textfsm_aos-1.1.3.dist-info/METADATA
textfsm_aos-1.1.3.dist-info/WHEEL
textfsm_aos-1.1.3.dist-info/RECORD
