Metadata-Version: 2.1
Name: textfsm-aos
Version: 1.1.3
Summary: Alcatel-Lucent Enterprise AOS CLI parsing (TextFSM)
Home-page: https://github.com/jefvantongerloo/textfsm-aos
License: Apache-2.0
Keywords: network automation,textfsm,scraping,Alcatel-Lucent Enterprise,infrastructure
Author: Jef Vantongerloo
Author-email: jefvantongerloo@gmail.com
Requires-Python: >=3.8
Classifier: License :: OSI Approved :: Apache Software License
Classifier: Programming Language :: Python :: 3
Classifier: Programming Language :: Python :: 3.8
Classifier: Programming Language :: Python :: 3.9
Classifier: Programming Language :: Python :: 3.10
Classifier: Programming Language :: Python :: 3.11
Requires-Dist: PyYAML (>=6.0,<7.0)
Requires-Dist: textfsm (>=1.1.0,<2.0.0)
Project-URL: Repository, https://github.com/jefvantongerloo/textfsm-aos
